README.md
setup.py
prt_phasecurve/__init__.py
prt_phasecurve/fort_spec.f90
prt_phasecurve/mu.py
prt_phasecurve/phase_curve.py
prt_phasecurve/spec_calc.py
prt_phasecurve.egg-info/PKG-INFO
prt_phasecurve.egg-info/SOURCES.txt
prt_phasecurve.egg-info/dependency_links.txt
prt_phasecurve.egg-info/requires.txt
prt_phasecurve.egg-info/top_level.txt