Metadata-Version: 2.1
Name: prt-phasecurve
Version: 0.1.7
Summary: module that creates phasecurves using pRT
Home-page: https://github.com/AaronDavidSchneider/prt_phasecurve
Author: Aaron David Schneider
Author-email: aarondavid.schneider@nbi.ku.dk
License: MIT
